{"syncToSong": true, "loop": true, "frames": [{"position": {"x": 1.3486, "y": 1.8825, "z": -4.6999}, "rotation": {"x": 0.0, "y": 350.6679, "z": 0.0}, "FOV": 75.0, "holdTime": 0, "transition": "Eased", "duration": 10.0}, {"position": {"x": 1.3486, "y": 1.8825, "z": -4.6999}, "rotation": {"x": 0.0, "y": 350.6679, "z": 0.0}, "FOV": 75.0, "holdTime": 10.0, "transition": "Eased", "duration": 10.0}, {"position": {"x": -1.0752, "y": 1.7171, "z": -4.6749}, "rotation": {"x": 0.0, "y": 27.1039, "z": 0.0}, "FOV": 75.0, "holdTime": 10.0, "transition": "Eased", "duration": 10.0}, {"position": {"x": 0.1542, "y": 2.494, "z": -4.8351}, "rotation": {"x": 15.8371, "y": 0.0, "z": 0.0}, "FOV": 75.0, "holdTime": 10.0, "transition": "Eased", "duration": 10.0}, {"position": {"x": 1.0295, "y": 2.2197, "z": -2.8289}, "rotation": {"x": 11.1418, "y": 344.9715, "z": 0.0}, "FOV": 74.1300049, "holdTime": 10.0, "transition": "Eased", "duration": 10.0}, {"position": {"x": -1.0295, "y": 2.2197, "z": -2.8289}, "rotation": {"x": 11.1418, "y": 40.9715, "z": 0.0}, "FOV": 74.1300049, "holdTime": 10.0, "transition": "Eased", "duration": 10.0}, {"position": {"x": 0.1542, "y": 2.494, "z": -4.8351}, "rotation": {"x": 15.8371, "y": 0.0, "z": 0.0}, "FOV": 75.0, "holdTime": 10.0, "transition": "Eased", "duration": 10.0}]}
